aicommit/__init__.py
aicommit/_types.py
aicommit/aicommit.toml
aicommit/cli.py
aicommit/cmd.py
aicommit/config_manager.py
aicommit/const.py
aicommit/exceptions.py
aicommit/hook.py
aicommit/llm_client.py
aicommit/main.py
aicommit/message_generator.py
aicommit/prepare-commit-msg
aicommit/support_keys.py
aicommit/utils.py
gptcommits-0.0.1.dist-info/METADATA
gptcommits-0.0.1.dist-info/WHEEL
gptcommits-0.0.1.dist-info/entry_points.txt
gptcommits-0.0.1.dist-info/licenses/LICENSE
gptcommits-0.0.1.dist-info/RECORD
