Metadata-Version: 2.1
Name: gptcommits
Version: 0.0.1
Summary: aicommit: A tool that leverages AI to automatically generate Git commit messages.
Keywords: python
Author-Email: belingud <im.victor@qq.com>
License: MIT license
Project-URL: Homepage, https://belingud.github.io/aicommit/
Project-URL: Repository, https://github.com/belingud/aicommit
Project-URL: Documentation, https://belingud.github.io/aicommit/
Requires-Python: <4.0,>=3.9
Requires-Dist: gitpython>=3.1.43
Requires-Dist: click>=8.1.7
Requires-Dist: litellm>=1.43.0
Requires-Dist: tomlkit>=0.13.0
Requires-Dist: tenacity>=9.0.0
Requires-Dist: orjson>=3.10.6
